django_watchfiles/__init__.py
django_watchfiles/py.typed
makavafal_django_watchfiles-0.0.1.dist-info/METADATA
makavafal_django_watchfiles-0.0.1.dist-info/WHEEL
makavafal_django_watchfiles-0.0.1.dist-info/top_level.txt
makavafal_django_watchfiles-0.0.1.dist-info/RECORD
