Metadata-Version: 2.1
Name: makavafal-django-watchfiles
Version: 0.0.1
Summary: Use watchfiles in Django’s autoreloader.
Home-page: https://github.com/adamchainz/django-watchfiles
Author: Adam Johnson
Author-email: me@adamj.eu
License: MIT
Project-URL: Changelog, https://github.com/adamchainz/django-watchfiles/blob/main/HISTORY.rst
Project-URL: Twitter, https://twitter.com/adamchainz
Requires-Python: >=3.7
Requires-Dist: Django (>=2.2)
Requires-Dist: watchfiles
